dtocean_economics/__init__.py
dtocean_economics-2.0.0.dist-info/METADATA
dtocean_economics-2.0.0.dist-info/WHEEL
dtocean_economics-2.0.0.dist-info/RECORD
