Metadata-Version: 2.1
Name: dtocean-economics
Version: 2.0.0
Summary: Economic assessment module for the DTOcean tools
Author: Mathew Topper
Author-email: damm_horse@yahoo.co.uk
Requires-Python: >=3.13,<4.0
Classifier: Programming Language :: Python :: 3
Classifier: Programming Language :: Python :: 3.13
